lifegrid/main.py
lifegrid/patterns.py
lifegrid/version.py
lifegrid/automata/__init__.py
lifegrid/automata/ant.py
lifegrid/automata/base.py
lifegrid/automata/briansbrain.py
lifegrid/automata/conway.py
lifegrid/automata/generations.py
lifegrid/automata/highlife.py
lifegrid/automata/immigration.py
lifegrid/automata/lifelike.py
lifegrid/automata/rainbow.py
lifegrid/automata/wireworld.py
lifegrid/gui/__init__.py
lifegrid/gui/app.py
lifegrid/gui/config.py
lifegrid/gui/rendering.py
lifegrid/gui/state.py
lifegrid/gui/ui.py
lifegrid-2.0.0.dist-info/licenses/LICENSE
lifegrid-2.0.0.dist-info/METADATA
lifegrid-2.0.0.dist-info/WHEEL
lifegrid-2.0.0.dist-info/entry_points.txt
lifegrid-2.0.0.dist-info/top_level.txt
lifegrid-2.0.0.dist-info/RECORD
