Metadata-Version: 2.4
Name: lifegrid
Version: 2.0.0
Summary: An interactive Tkinter-based workbench for experimenting with cellular automata
Author-email: James-HoneyBadger <your-email@example.com>
License: MIT
Project-URL: Homepage, https://github.com/James-HoneyBadger/LifeGrid
Project-URL: Repository, https://github.com/James-HoneyBadger/LifeGrid.git
Project-URL: Documentation, https://github.com/James-HoneyBadger/LifeGrid/tree/master/docs
Project-URL: Issues, https://github.com/James-HoneyBadger/LifeGrid/issues
Keywords: cellular-automata,conway-game-of-life,tkinter,simulation,interactive
Classifier: Development Status :: 4 - Beta
Classifier: Intended Audience :: Developers
Classifier: Intended Audience :: Science/Research
Classifier: License :: OSI Approved :: MIT License
Classifier: Natural Language :: English
Classifier: Operating System :: OS Independent
Classifier: Programming Language :: Python
Classifier: Programming Language :: Python :: 3
Classifier: Programming Language :: Python :: 3.13
Classifier: Programming Language :: Python :: 3.14
Classifier: Topic :: Scientific/Engineering
Classifier: Topic :: Software Development :: Libraries :: Python Modules
Requires-Python: >=3.13
License-File: LICENSE
Requires-Dist: numpy>=1.24.0
Requires-Dist: scipy>=1.11.0
Requires-Dist: Pillow>=10.0.0
Provides-Extra: dev
Requires-Dist: pytest>=7.4.0; extra == "dev"
Requires-Dist: mypy>=1.0.0; extra == "dev"
Requires-Dist: pylint>=2.17.0; extra == "dev"
Dynamic: license-file
